gitaudit/REQUIREMENTS
gitaudit/VERSION
gitaudit/__init__.py
gitaudit/exceptions.py
gitaudit/root.py
gitaudit/analysis/__init__.py
gitaudit/analysis/changelog/__init__.py
gitaudit/analysis/changelog/changelog.py
gitaudit/analysis/integration_flow/__init__.py
gitaudit/analysis/integration_flow/int_flow.py
gitaudit/analysis/integration_flow/required_status_checks.py
gitaudit/analysis/integration_flow/utils.py
gitaudit/analysis/merge_diff/__init__.py
gitaudit/analysis/merge_diff/matchers.py
gitaudit/analysis/merge_diff/merge_diff.py
gitaudit/analysis/merge_diff/pruners.py
gitaudit/analysis/merge_diff/report.py
gitaudit/analysis/merge_diff/report_templates/combined_report.html
gitaudit/analysis/merge_diff/report_templates/match_table.html
gitaudit/analysis/merge_diff/report_templates/prune_table.html
gitaudit/analysis/merge_diff/report_templates/single_report.html
gitaudit/analysis/merge_diff/report_templates/statistics_table.html
gitaudit/analysis/merge_diff/report_templates/unmatched_table.html
gitaudit/analysis/merge_diff/report_templates/css/adapted.min.css
gitaudit/analysis/merge_diff/report_templates/macros/change_log_entry.html
gitaudit/analysis/sha_version_mapper/__init__.py
gitaudit/analysis/sha_version_mapper/sha_version_mapper.py
gitaudit/analysis/statistics/__init__.py
gitaudit/analysis/statistics/statistics.py
gitaudit/branch/__init__.py
gitaudit/branch/hierarchy.py
gitaudit/branch/plotting.py
gitaudit/branch/prune.py
gitaudit/branch/serialization.py
gitaudit/branch/submodule.py
gitaudit/branch/tree.py
gitaudit/branch/tree_creator.py
gitaudit/git/__init__.py
gitaudit/git/change_log_entry.py
gitaudit/git/controller.py
gitaudit/github/__init__.py
gitaudit/github/graphql_base.py
gitaudit/github/graphql_objects.py
gitaudit/github/instance.py
gitaudit/render/__init__.py
gitaudit/render/change_log.py
gitaudit/render/templates/adapted.min.css
gitaudit/render/templates/change_log.html
gitaudit/render/templates/change_log_entries.html
gitaudit-0.19.13.dist-info/LICENSE
gitaudit-0.19.13.dist-info/METADATA
gitaudit-0.19.13.dist-info/WHEEL
gitaudit-0.19.13.dist-info/top_level.txt
gitaudit-0.19.13.dist-info/RECORD
