Metadata-Version: 2.1
Name: gitaudit
Version: 0.19.13
Summary: Analyse git repositories
Home-page: https://github.com/MatthiasRieck/gitaudit
Author: Matthias Rieck
Author-email: Matthias.Rieck@tum.de
License-File: LICENSE
Requires-Dist: pydantic
Requires-Dist: pytz
Requires-Dist: humps
Requires-Dist: requests
Requires-Dist: svgdiagram
Requires-Dist: jinja2
Requires-Dist: rich
